createmeal/__init__.py
createmeal/composite/__init__.py
createmeal/composite/node.py
createmeal/composite/node_factory.py
createmeal/composite/self_closing_tag_node.py
createmeal/composite/string_node.py
createmeal-0.1.0.dist-info/LICENSE
createmeal-0.1.0.dist-info/METADATA
createmeal-0.1.0.dist-info/WHEEL
createmeal-0.1.0.dist-info/top_level.txt
createmeal-0.1.0.dist-info/RECORD
