Metadata-Version: 2.1
Name: createmeal
Version: 0.1.0
Summary: A library to render HTML
Home-page: https://github.com/createmeal/createmeal-py
Author: Julio Cezar da Silva
Author-email: jcezardasilva@outlook.com
License: UNKNOWN
Project-URL: Bug Tracker, https://github.com/createmeal/createmeal-py/issues
Platform: UNKNOWN
Classifier: Programming Language :: Python :: 3.9
Classifier: Programming Language :: Python :: 3.10
Classifier: Intended Audience :: Developers
Classifier: License :: OSI Approved :: MIT License
Classifier: Operating System :: OS Independent
Classifier: Development Status :: 4 - Beta
Classifier: Topic :: Internet
Classifier: Topic :: Software Development :: Libraries :: Python Modules
Requires-Python: >=3.9
License-File: LICENSE
